Metadata-Version: 2.1
Name: plpy-wrapper
Version: 0.1
Summary: UNKNOWN
Home-page: https://github.com/skamensky/plpy-wrapper/
Author: Shmuel Kamensky
License: MIT
Keywords: postgres plpython plpy wrapper
Platform: UNKNOWN
Requires-Python: >=3.7, <=3.8
Provides-Extra: pypipublish
Provides-Extra: docs
